pip_migrate/__init__.py
pip_migrate/pip_migrate.py
pip_migrate-1.0.2.dist-info/METADATA
pip_migrate-1.0.2.dist-info/WHEEL
pip_migrate-1.0.2.dist-info/entry_points.txt
pip_migrate-1.0.2.dist-info/top_level.txt
pip_migrate-1.0.2.dist-info/RECORD
