Metadata-Version: 2.1
Name: pip-migrate
Version: 1.0.2
Summary: A tool to backup and migrate Python packages
Home-page: https://github.com/crushr3sist/pip-migrate
Author: Rohaan Ahmed
Author-email: silent.death3500@gmail.com
Keywords: pip migrate backup restore python packages utility tool
Classifier: Development Status :: 3 - Alpha
Classifier: License :: OSI Approved :: MIT License
Classifier: Programming Language :: Python :: 3
Classifier: Programming Language :: Python :: 3.6
Classifier: Programming Language :: Python :: 3.7
Classifier: Programming Language :: Python :: 3.8
Classifier: Programming Language :: Python :: 3.9
Classifier: Programming Language :: Python :: 3.10
Classifier: Programming Language :: Python :: 3.11
Requires-Python: >=3.6
Requires-Dist: setuptools
Requires-Dist: wheel
Requires-Dist: progress
